random_name_generator/__init__.py
random_name_generator/cli.py
random_name_generator/constants.py
random_name_generator/errors.py
random_name_generator/generators.py
random_name_generator/selectors.py
python_random_name_generator-0.0.6.dist-info/METADATA
python_random_name_generator-0.0.6.dist-info/WHEEL
python_random_name_generator-0.0.6.dist-info/entry_points.txt
python_random_name_generator-0.0.6.dist-info/top_level.txt
python_random_name_generator-0.0.6.dist-info/RECORD
