Metadata-Version: 2.1
Name: python-random-name-generator
Version: 0.0.6
Summary: UNKNOWN
Home-page: https://github.com/vitaliy-diachkov/python-random-name-generator
Author: Vitaliy Diachkov
Author-email: diachkovspecial@gmail.com
License: UNKNOWN
Platform: UNKNOWN
